ads4gpts_langgraph_agent/__init__.py
ads4gpts_langgraph_agent/agent.py
ads4gpts_langgraph_agent/llms.py
ads4gpts_langgraph_agent/prompts.py
ads4gpts_langgraph_agent/state.py
ads4gpts_langgraph_agent/tools.py
ads4gpts_langgraph_agent-0.1.10.dist-info/LICENSE
ads4gpts_langgraph_agent-0.1.10.dist-info/METADATA
ads4gpts_langgraph_agent-0.1.10.dist-info/WHEEL
ads4gpts_langgraph_agent-0.1.10.dist-info/top_level.txt
ads4gpts_langgraph_agent-0.1.10.dist-info/RECORD
